CHANGES.txt
COPYRIGHT.txt
LICENSE.txt
README.txt
bootstrap.py
buildout.cfg
setup.py
src/gocept/__init__.py
src/gocept.registration.egg-info/PKG-INFO
src/gocept.registration.egg-info/SOURCES.txt
src/gocept.registration.egg-info/dependency_links.txt
src/gocept.registration.egg-info/namespace_packages.txt
src/gocept.registration.egg-info/not-zip-safe
src/gocept.registration.egg-info/requires.txt
src/gocept.registration.egg-info/top_level.txt
src/gocept/registration/README.txt
src/gocept/registration/__init__.py
src/gocept/registration/configure.zcml
src/gocept/registration/email.py
src/gocept/registration/ftesting.zcml
src/gocept/registration/i18n.py
src/gocept/registration/interfaces.py
src/gocept/registration/registrations.py
src/gocept/registration/testing.py
src/gocept/registration/tests.py
src/gocept/registration/browser/__init__.py
src/gocept/registration/browser/confirmation.pt
src/gocept/registration/browser/confirmation_error.pt
src/gocept/registration/browser/registration.py
src/gocept/registration/demo/README.txt
src/gocept/registration/demo/__init__.py
src/gocept/registration/demo/application.zcml
src/gocept/registration/demo/template.pt