Metadata-Version: 1.0
Name: gocept.registration
Version: 0.3.0
Summary: User self-registration
Home-page: http://pypi.python.org/pypi/gocept.registration/
Author: Christian Theune, Stephan Richter and others
Author-email: mail@gocept.com
License: ZPL 2.1
Keywords: zope3 gocept user registration
Platform: UNKNOWN
Classifier: Development Status :: 4 - Beta
Classifier: Environment :: Web Environment
Classifier: Intended Audience :: Developers
Classifier: License :: OSI Approved :: Zope Public License
Classifier: Programming Language :: Python
Classifier: Natural Language :: English
Classifier: Operating System :: OS Independent
Classifier: Topic :: Internet :: WWW/HTTP
Classifier: Framework :: Zope3
